cadmus/__init__.py
cadmus/cache.py
cadmus/cache_test.py
cadmus/database.py
cadmus/model.py
cadmus/version.py
zf_cadmus-0.0.2.dist-info/LICENSE
zf_cadmus-0.0.2.dist-info/METADATA
zf_cadmus-0.0.2.dist-info/WHEEL
zf_cadmus-0.0.2.dist-info/top_level.txt
zf_cadmus-0.0.2.dist-info/RECORD
