Metadata-Version: 2.1
Name: zf-cadmus
Version: 0.0.2
Summary: pd supercharges your development workflows
Author: zeffmuks
Author-email: zeffmuks@gmail.com
License-File: LICENSE
Requires-Dist: annotated-types
Requires-Dist: anyio
Requires-Dist: Authlib
Requires-Dist: certifi
Requires-Dist: cffi
Requires-Dist: charset-normalizer
Requires-Dist: cryptography
Requires-Dist: distro
Requires-Dist: h11
Requires-Dist: httpcore
Requires-Dist: httpx
Requires-Dist: idna
Requires-Dist: loguru
Requires-Dist: openai
Requires-Dist: pycparser
Requires-Dist: pydantic
Requires-Dist: pydantic-core
Requires-Dist: requests
Requires-Dist: sniffio
Requires-Dist: tqdm
Requires-Dist: typing-extensions
Requires-Dist: urllib3
Requires-Dist: validators
Requires-Dist: weaviate-client
